samuranium/WebElement.py
samuranium/__init__.py
samuranium/__main__.py
samuranium/runner.py
samuranium/steps.py
samuranium/mobile/AppiumServerManager.py
samuranium/mobile/__init__.py
samuranium/reporter/__init__.py
samuranium/reporter/templates/__init__.py
samuranium/reporter/templates/report.html
samuranium/utils/__init__.py
samuranium/utils/config.py
samuranium/utils/general.py
samuranium/utils/logger.py
samuranium/utils/paths.py
samuranium/utils/time.py
samuranium_cli/__init__.py
samuranium_cli/__main__.py
samuranium_cli/bdd.py
samuranium_cli/templates.py
samuranium_cli/utils.py
tests/__init__.py
tests/test_android.py
tests/test_browser.py
tests/test_samu_todo.py
tests/test_steps.py
samuranium-0.0.2.dist-info/LICENSE
samuranium-0.0.2.dist-info/METADATA
samuranium-0.0.2.dist-info/WHEEL
samuranium-0.0.2.dist-info/entry_points.txt
samuranium-0.0.2.dist-info/top_level.txt
samuranium-0.0.2.dist-info/RECORD
