Metadata-Version: 2.1
Name: samuranium
Version: 0.0.2
Summary: A test automation framework
Home-page: https://github.com/malazay/samuranium
Author: Alexis Giovoglanian
Author-email: alexisgiovoglanian@infovalue.com.ar
License: UNKNOWN
Platform: UNKNOWN
Classifier: Programming Language :: Python :: 3
Classifier: License :: OSI Approved :: GNU General Public License v3 (GPLv3)
Classifier: Operating System :: OS Independent
Requires-Python: >=3.7
Requires-Dist: selenium
Requires-Dist: webdriver-manager
Requires-Dist: behave
Requires-Dist: jinja2
Requires-Dist: appium-python-client
